autocontext/__init__.py
autocontext/context.py
tests/__init__.py
tests/__main__.py
tests/basic_test.py
autocontext-0.0.2.dist-info/AUTHORS.rst
autocontext-0.0.2.dist-info/LICENSE
autocontext-0.0.2.dist-info/METADATA
autocontext-0.0.2.dist-info/WHEEL
autocontext-0.0.2.dist-info/top_level.txt
autocontext-0.0.2.dist-info/RECORD
